Workbook

Sheet Risposte del modulo 1
A1: Informazioni cronologiche | B1: Acconsenti a partecipare a questo studio? | C1: Attualmente lavori completamente da remoto? | D1: Quanti anni hai? | E1: Lavoravi già completamente da remoto quando avevi circa 35 anni? | F1: Genere | G1: Paese (o città) in cui vivi | H1: Che lavoro / ruolo hai? | I1: Con chi vivi? | J1: Quanto spesso fai attività fisica o sport? | K1: Descrivi la tua ultima giornata lavorativa tipica, da quando ti sei svegliato/a a quando hai smesso di lavorare. | L1: Come segni l'inizio e la fine della tua giornata lavorativa? Hai abitudini o rituali? | M1: Nell'ultimo mese, quanto spesso ti è capitato di… […continuare a lavorare oltre l'orario previsto] | N1: Nell'ultimo mese, quanto spesso ti è capitato di… […controllare messaggi di lavoro fuori orario] | O1: Nell'ultimo mese, quanto spesso ti è capitato di… […pranzare alla scrivania o saltare il pranzo] | P1: Nell'ultimo mese, quanto spesso ti è capitato di… […sentirti incapace di staccare dal lavoro] | Q1: Nell'ultimo mese, quanto spesso ti è capitato di… […passare un'intera giornata senza uscire di casa] | R1: Pensa all'ultima volta in cui il lavoro ha invaso il tuo tempo personale. Cosa è successo e come ti sei sentito/a? | S1: In una settimana normale, con quante persone parli di persona (non in videochiamata), escluse quelle con cui vivi? | T1: Come interagisci con i colleghi al di là delle attività strettamente lavorative? (anche più risposte) | U1: Quanto ti senti in connessione con i tuoi colleghi? | V1: Quanto sei soddisfatto/a della tua vita sociale fuori dal lavoro? | W1: Come ha cambiato la tua vita sociale il lavoro da remoto? Raccontaci aspetti positivi e negativi. | X1: Raccontaci l'ultima volta in cui ti sei sentito/a solo/a o isolato/a a causa del modo in cui lavori. Se non ti capita, cosa pensi che ti protegga? | Y1: Cosa fai attualmente per tenere separati lavoro e vita privata? | Z1: Quali di questi usi per concentrazione, gestione del tempo, benessere o socialità? (anche più risposte) | AA1: Hai mai provato qualcosa (un'abitudine, uno strumento, un gruppo, una routine) per migliorare i tuoi confini o la tua vita sociale e poi hai smesso? Cosa e perché? | AB1: Se potessi cambiare una cosa di come il lavoro da remoto influisce sul tuo benessere, quale sarebbe e perché? | AC1: Dove lavori più spesso? | AD1: Quanti giorni a settimana lavori fuori casa? | AE1: Cosa ti ha spinto a iniziare a lavorare lì invece che a casa? | AF1: Interagisci con le altre persone che lavorano lì? Descrivi l'ultima interazione significativa che hai avuto (o perché non succede). | AG1: In cosa sono diversi l'inizio e la fine della giornata quando lavori lì rispetto a quando lavori a casa? | AH1: Cosa non funziona per te in questi spazi (costi, rumore, privacy, persone, distanza…)? | AI1: Quale di queste descrive meglio i tuoi orari di lavoro? | AJ1: In che fascia oraria (ora locale) lavori di solito? | AK1: Come organizzi sonno, pasti e tempo libero attorno a questi orari? | AL1: Raccontaci l'ultima volta in cui i tuoi orari ti hanno fatto perdere o rinunciare a qualcosa di sociale (una cena, un evento, lo sport…). Cosa è successo? | AM1: Quando i tuoi colleghi sono online e tu no (o viceversa), come gestisci i messaggi e la sensazione di dover essere reperibile? | AN1: Le persone intorno a te (partner, amici, coinquilini, famiglia) si adattano ai tuoi orari? In che modo? | AO1: Da quanto tempo lavori completamente da remoto? | AP1: Come sono cambiate le tue abitudini tra lavoro e tempo libero rispetto ai primi mesi completamente da remoto? | AQ1: C'è stato un periodo in cui il lavoro da remoto ti è pesato più del solito? Cosa stava succedendo e cosa ti ha aiutato? | AR1: Cosa hai dovuto imparare a tue spese che diresti a chi inizia oggi a lavorare completamente da remoto? | AS1: Hai mai pensato di tornare in ufficio o a un lavoro ibrido? Perché, e cosa hai deciso? | AT1: Per mostrarti le domande finali giuste, in che fascia d'età sei? | AU1: Rispetto a quando avevi meno di 35 anni, come è cambiato il modo in cui bilanci lavoro, tempo libero e vita sociale? | AV1: Cosa è cambiato nelle tue priorità negli ultimi anni (carriera, famiglia, salute, amicizie) e come si incastra il lavoro da remoto con esse? | AW1: Nella tua fase di vita attuale, cosa rende più facile o più difficile conoscere persone nuove o mantenere i contatti con gli amici? | AX1: I tuoi amici coetanei hanno ritmi diversi dai tuoi (lavoro in ufficio, figli, turni)? Come influisce su quando e come vi vedete? | AY1: C'è qualcosa che fai oggi per proteggere il tuo benessere che avresti voluto iniziare prima? Perché? | AZ1: In cosa pensi che la tua esperienza del lavoro da remoto sia diversa da quella dei colleghi ventenni? | BA1: Prima di passare completamente al remoto, quanti anni avevi lavorato in ufficio o in presenza? | BB1: Cosa ti ha portato a lavorare completamente da remoto in questa fase della tua vita e carriera? | BC1: Hai notato colleghi più giovani in difficoltà con i confini o l'isolamento in modi che a te non capitano? Raccontaci una situazione concreta. | BD1: Ti capita di supportare o consigliare colleghi più giovani da remoto (formalmente o informalmente)? Come avviene a distanza? | BE1: Quali abitudini o regole hai portato dalla vita d'ufficio che ti aiutano ancora oggi? | BF1: Come ha influito il lavoro da remoto sulla tua salute fisica (movimento, postura, sonno, energia) e cosa fai al riguardo? | BG1: Quanto ti senti a tuo agio con gli strumenti digitali del lavoro da remoto (chat, videochiamate, strumenti asincroni)? Ce n'è uno che ti rende più difficile staccare? | BH1: In cosa pensi che la tua esperienza del lavoro da remoto sia diversa da quella dei colleghi più giovani? | BI1: Se in passato hai lavorato in ufficio: cosa ti manca e cosa invece non ti manca per niente? | BJ1: Negli anni, come hai costruito la tua cerchia di amicizie, e quanto viene dal lavoro? | BK1: In che modo famiglia o altre responsabilità influenzano i confini tra lavoro e tempo personale? | BL1: C'è qualcos'altro sul lavoro da remoto, la vita sociale o i confini che vorresti raccontarci? | BM1: Saresti disponibile per una breve intervista di approfondimento (30–45 min, di persona o in videochiamata)? | BN1: Se sì, lascia la tua email o un contatto social per ricontattarti | BO1: Se sei a Torino o in zone limitrofe, sei disponibile ad essere intervistato dal vivo ?
A2: 46308.442 | B2: Sì, acconsento | C2: Sì, completamente da remoto (al massimo pochi giorni in ufficio all'anno) | D2: 30–35 | F2: Uomo | G2: La Loggia (TO) | H2: Libero professionista - Content creator e copywriter | I2: Con il/la partner | J2: 3 o più volte a settimana | K2: Passeggiata, lavoro creativo al mattino per me e per clienti, palestra + pranzo, dormita strategica, ancora lavoro blando fino alle 16-17. | L2: Nella bella stagione una passeggiata prima di iniziare a lavorare | M2: Mai | N2: Sempre | O2: Mai | P2: Mai | Q2: Raramente | R2: Non è successo | S2: 3–5 | T2: Interagisco online con il mio socio | U2: 4 | V2: 4 | W2: Mi ha dato il controllo della mia intera esistenza, direi che è sufficiente. | X2: Mi capita raramente perché fondamentalmente sto bene da solo. Nella bella stagione sento più l'esigenza di uscire e socializzare. | Y2: Non lo faccio, ma il lavoro non invade la vita privata perché non arriva mai a picchi troppo stressanti. | Z2: Nessuno di questi | AA2: No, ma proverei. | AB2: Vorrei aver ereditato case sparse per l'Italia come i migliori figli di papà per lavorare da posti diversi durante l'anno senza spendere tonnellate di denaro per farlo. | AC2: A casa, in una stanza usata solo per lavorare | AI2: Orari standard, stesso fuso del mio team | AO2: Più di 5 anni | AP2: Non sono cambiate, non ho orari definiti ma magari lavoro, faccio attività fisica, poi lavoro ancora, poi mi rilasso leggendo o giocando ai videogiochi. | AQ2: Tendenzialmente più d'inverno con il buio e il brutto tempo, a volte ti senti "Imprigionato". | AR2: Fai in modo di avere una routine per rimanere stabile mentalmente e pratica assolutamente sport. | AS2: No, manco per sbaglio. | AT2: Meno di 36 | BL2: - | BM2: Sì | BN2: altimani.luca.web@gmail.com
A3: 46308.659 | B3: Sì, acconsento | C3: Sì, completamente da remoto (al massimo pochi giorni in ufficio all'anno) | D3: 25–29 | F3: Donna | G3: Modena | H3: Software Engineer | I3: Con il/la partner | J3: 1–2 volte a settimana | K3: Mi sono svegliata alle 9. Alle 9:15 ho avuto il solito meeting di allineamento giornaliero (daily) fino alle 10. Alle 10 ho fatto colazione. Ho lavorato in autonomia fino alle 12. Alle 12 ho avuto un meeting. Mentre seguivo il meeting ho cucinato il pranzo. Alle 13 ho pranzato con la mia compagna. Alle 14:30 ho ripreso a lavorare. Alle 16:30 pausa caffè di 15 minuti. Ho lavorato fino alle 18. | L3: Accendo e spengo il PC ed esco dal mio studio. | M3: A volte | N3: Raramente | O3: Mai | P3: A volte | Q3: Spesso | R3: Ansiosa a causa di alcune deadlines. | S3: 6 o più | T3: Canali di chat informali (es. #random su Slack), Pause caffè virtuali / call sociali, Incontri dal vivo, retreat o offsite | U3: 3 | V3: 4 | W3: In meglio! Più flessibilit e possibilità di vedere chi voglio dove voglio. | Y3: Ho un luogo adibito solo al lavoro, il mio studio. | Z3: Non disturbare o orari per le notifiche, Un dispositivo o account separato per il lavoro | AB3: Non saprei | AC3: A casa, in una stanza usata solo per lavorare | AI3: Orari standard, stesso fuso del mio team | AO3: 1–3 anni | AT3: Meno di 36 | BM3: No
A4: 46308.665 | B4: Sì, acconsento | C4: Sì, completamente da remoto (al massimo pochi giorni in ufficio all'anno) | D4: 25–29 | F4: Uomo | G4: Corato (BA) | H4: Software developer | I4: Con i miei genitori / famiglia d'origine | J4: 3 o più volte a settimana | K4: Colazione, call del mattino, caffè, lavoro, se ho tempi morti leggo qualcosa, pranzo, lavoro e poi o esco o vado in palestra | L4: Mi faccio un caffè | M4: Mai | N4: Raramente | O4: Mai | P4: Mai | Q4: A volte | R4: Non è successo per fortuna | S4: 3–5 | T4: Pause caffè virtuali / call sociali | U4: 3 | V4: 4 | W4: In positivo perché mi dà più tempo libero e magari la domenica posso fare più tardi o tipo uscire d rientrare senza problemi all'1 di notte ma allo stesso tempo mi ha spinto ad ampliare la rete sociale. | X4: Mi protegge il fatto che appena stacco ho modo di andare in palestra, ho degli amici con cui o mi vedo o sono sempre in contatto | Y4: Stacco e me ne frego | Z4: Nessuno di questi | AA4: No | AB4: Magari vorrei un rapporto meno distaccato con gli altri colleghi visto che tranne con uno, con gli altri non capita di parlare di cose che vanno oltre il lavoro | AC4: A casa, in una stanza usata solo per lavorare | AI4: Orari standard, stesso fuso del mio team | AO4: 1–3 anni | AT4: Meno di 36 | BL4: È utile per il discorso costi (visto I prezzi del carburante) ma allo stesso tempo devi saper gestire perché stare chiuso in casa senza occasioni sociali al di fuori dell'orario di lavoro non fa bene | BM4: Sì | BN4: gramegna.simone@gmail.com
A5: 46308.666 | B5: Sì, acconsento | C5: Ibrido: vado in ufficio o in sede regolarmente
A6: 46308.674 | B6: Sì, acconsento | C6: Sì, completamente da remoto (al massimo pochi giorni in ufficio all'anno) | D6: 30–35 | F6: Uomo | G6: Amsterdam | H6: Lead Account Manager | I6: Con il/la partner | J6: 3 o più volte a settimana | K6: Sveglia alle 8.00, colazione con calma, 9.00 si inizia a lavorare da casa. Parlo con i colleghi e con il mio partner che anche lavora da casa. Pausa pranzo di 1h verso le 12.00. smetto di lavorare alle 17.00. Un paio di volte a settimana faccio lo stesso ma vado a lavorare in un coworking space dove capita di icnntrare amici. | L6: Inizio con il caffe' e con lo svuotare la lavastoviglia pulita, la fine mi preparo e vado in palestra. | M6: A volte | N6: Mai | O6: A volte | P6: Mai | Q6: Raramente | R6: Capita molto poco, ho un'ottimo work life balance. Quando e' successo non ho provato molto disturbo in quanto e' successo veramente poche volte. | S6: 1–2 | T6: Canali di chat informali (es. #random su Slack), Pause caffè virtuali / call sociali, Incontri dal vivo, retreat o offsite | U6: 5 | V6: 4 | W6: Positivi: possibilita' di passare tempo di qualita' con la mia famiglia che non vive nella citta' in cui lavoro, passare del tempo con amici di sempre, viaggiare, avere piu' tempo per la gestione della casa, della mia vita privata, nelle mie passioni. Molti meno costi di logistica e pranzi etc. Mangio piu' sano in quanto ho tempo per cucinare. Dormo di piu'. Riesco a fare sport. Negativi: Meno interazioni umane. | X6: Mi protegge la mia routine, andare a lavorare ogni tanto in cowroking, viaggiare molto sia per lavoro sia per passione e poter lavorare da dove mi pare. Avere un casa che spesso accoglie amici e familiari. | Y6: Rispetto gli orari, uso spazi diversi per lavorare. | Z6: Blocchi nel calendario, Timer di concentrazione / Pomodoro, Non disturbare o orari per le notifiche, Fitness tracker o app sportive, Un dispositivo o account separato per il lavoro | AA6: No | AB6: Non cambierei nulla, per me lavorare da remoto e' un diritto che tutti dovrebbero avere. E' liberta', e' puro benessere e sono estrememnete grato di poter essere parte di questo cluster di persone. | AC6: Cambia spesso / in viaggio | AD6: 2–3 giorni | AE6: Cambiare area | AF6: si integraggisco, parliamo di tutto. Spesso sono amici. | AG6: Sono due mindset diversi. Quando lavoro da casa spesso a fine giornata esco comuqnue, finisco alle 17 e quindi ho ancora tanet ore d'avanti per fare tante altre cose. Quando lavoro fuori, spesso sono gia' molto stanco, quindi o mi fermo per un piccolo apertivo con amici o vado a giocare a tennis o se sono vicino al mare, vado a mare. | AH6: alcune volte costi | AI6: Orari standard, stesso fuso del mio team | AO6: Più di 5 anni | AP6: Molto, inizialemnte non ero molto diligente con il mio work life balance, poi ho imparato a gestirlo. | AR6: Impara a crearti spazi condivisi, una community , persone come te, impara la gestione del tempo. | AS6: MAI | AT6: Meno di 36 | BL6: Lavorare da remoto e' progresso. Continuate a lottare per questo diritto. | BM6: No
A7: 46308.676 | B7: Sì, acconsento | C7: Sì, completamente da remoto (al massimo pochi giorni in ufficio all'anno) | D7: 25–29 | F7: Uomo | G7: Mobile Alabama stati uniti | H7: Sales | I7: Con il/la partner | J7: 3 o più volte a settimana | K7: Sveglia alle 5 smesso alle 3 Pm nel mio studio, poche pause chiamate riunioni solite cose | L7: Caffè prima di iniziare | M7: Mai | N7: Mai | O7: Mai | P7: Mai | Q7: Raramente | R7: Stressato per i kpi sono uscito con mia moglie per non pensarci | S7: 6 o più | T7: Canali di chat informali (es. #random su Slack) | U7: 3 | V7: 5 | W7: Parlo meno con colleghi e li conosco meno, forse imparo meno velocemente ma son più performante perché perdo molto meno tempo | X7: Non mi sento mai solo, ho molto lavoro quindi questo mi protegge forse | Y7: Non entro mai nella stanza in cui lavoro al di fuori dell orario di lavoro | Z7: Nessuno di questi | AA7: No | AB7: Mi farebbe piacere vedere i miei colleghi almeno una volta al mese | AC7: A casa, in una stanza usata solo per lavorare | AI7: Orari standard, stesso fuso del mio team | AO7: Meno di 1 anno | AT7: Meno di 36 | BL7: No | BM7: Sì | BN7: matteo.pierangeli.97@gmail.com
A8: 46308.687 | B8: Sì, acconsento | C8: Sì, completamente da remoto (al massimo pochi giorni in ufficio all'anno) | D8: 30–35 | F8: Uomo | H8: Cybersecurity consultant | I8: Da solo/a | J8: 3 o più volte a settimana | K8: Call allineamento iniziale, svolgimento task, monitoraggio, allineamento colleghi, verifiche pomeridiane, stacco | L8: No | M8: Mai | N8: Raramente | O8: Mai | P8: Mai | Q8: Mai | R8: Un problema improvviso, può succedere. Son stato tranquillo, sapevo era un'eccezione e non la regola | S8: 3–5 | T8: Canali di chat informali (es. #random su Slack) | U8: 3 | V8: 5 | W8: Posso finalmente riprendere a fare sport dato che non devo sprecare ore di pendolarismo | X8: La libertà | Y8: Spengo notebook e telefono aziendale | Z8: Non disturbare o orari per le notifiche, Un dispositivo o account separato per il lavoro | AB8: N/A | AC8: A casa, in una stanza usata solo per lavorare | AI8: Orari standard, stesso fuso del mio team | AO8: 3–5 anni | AP8: Uguali | AQ8: Mai | AR8: Mettere per iscritto la modalità di lavoro evitando che questa abbia un termine | AS8: Sì, se fosse vicino a casa mia | AT8: Meno di 36 | BM8: No
A9: 46308.687 | B9: Sì, acconsento | C9: Sì, completamente da remoto (al massimo pochi giorni in ufficio all'anno) | D9: 30–35 | F9: Uomo | G9: Salerno | H9: Sviluppatore software | I9: Con il/la partner | J9: 3 o più volte a settimana | K9: Circa ore 10 mi sveglio, saluto il mio partner (che anche lavora da remoto) e inizio a lavorare Verso le 12 potrei fermarmi e fare una pausa per colazione o spuntino Ore 13.30 preparo il pranzo e finisco verso le 14.30/15.00 (pausa inclusa) Ore 16.00 solitamente riunioni con il team Ore 17.00 fine delle riunioni e faccio pausa (spuntino, 15 minuti di riposo), Ore 19.00 Fine lavoro | L9: Niente di particolare, inizio accendendo il PC, finisco quando non ho altri compiti rimasti per la giornata (a volte stacco prima, a volte dopo, a volte lascio il portatile acceso per alcuni controlli che magari faccio la sera) | M9: Spesso | N9: Sempre | O9: Mai | P9: Raramente | Q9: A volte | R9: Messaggi da colleghi che lavorano in timezone USA. Non mi pesa sinceramente- Se ho altro da fare stacco e basta, se non ho niente da fare (sono a casa o guardo un film o sto cucinando la cena) onestamente non mi pesa | S9: 6 o più | T9: Canali di chat informali (es. #random su Slack), Incontri dal vivo, retreat o offsite | U9: 4 | V9: 5 | W9: Ho energie per attività da svolgere dopo il lavoro. Ho lavorato a 50 minuti da casa (quando vivevo a torino, da piazza Massaua a lungo stura lazio) e non avevo tempo di fare nulla. A volte vado a pranzo fuori con amici. Altre volte vado a casa dai miei genitori per un pranzo. Se ho eventu Domenica sera - Giovedì sera non devo pensare che il giorno dopo mi devo alzare alle 7. Non ho rilevato aspetti negativi personalmente, probabilmente perchè vivo nella mia città natale e ho amici e attività al di fuori del lavoro | X9: Durante il COVID. Principalmente perchè mi ero trasferito per lavorare in sede in una città in cui non conoscevo nessuno, e non c'era possibilità di fare attività post-lavoro causa COVID | Y9: Onestamente non mi pesa se le due cose si sovrappongono. | Z9: Nessuno di questi | AA9: No, non ho rilevato questo problema | AB9: Al momento non cambierei nulla | AC9: A casa, in uno spazio condiviso (camera, cucina, soggiorno) | AI9: Lavoro con persone a più di 3 ore di differenza di fuso | AJ9: 10:30-18:30 | AK9: Dormo circa 8 ore prima di quando devo svegliarmi, vado in palestra attorno alle 19:30, mangio verso le 13:30. Nessun cambio particolare rispetto al solito lavoro da ufficio | AL9: Un problema lavorativo alle 18:00 ha richiesto più tempo del previsto. Ho preferito rinunciare alla palestra per riposarmi | AM9: A volte rispondo, ma sono consapevole che nessuno mi obbliga. E viceversa. | AN9: No, niente in particolare | AO9: 3–5 anni | AP9: Rimaste circa le stesse | AQ9: Solo durante il COVID, perchè vivevo in una città totalmente nuova. Poi mi sono trasferito nella città natale | AR9: Comprate una sedia da ufficio (non quelle schifezze da gaming) e non usate una sedia da cucina | AS9: Solo se raddoppiassi lo stipendio. Cosa impossibile nella zona in cui vivo | AT9: Meno di 36 | BL9: Dovrebbe essere un diritto per chi svolge un lavoro da PC. E spacciare lavoro da remoto un ibrido con 2 giorni in sede su Milano non ha senso. Ha tutti gli svantaggi di un trasferimento (a meno che non vivi vicino ovviamente) ma ti obbliga a lavorare isolato per il restante del tempo | BM9: No
A10: 46308.7 | B10: Sì, acconsento | C10: Sì, completamente da remoto (al massimo pochi giorni in ufficio all'anno) | D10: 36 o più | E10: No
A11: 46308.714 | B11: Sì, acconsento | C11: Sì, completamente da remoto (al massimo pochi giorni in ufficio all'anno) | D11: 25–29 | F11: Uomo | G11: England, Bristol | H11: Data Scientist | I11: Con coinquilini | J11: 3 o più volte a settimana | K11: Wake up 8:50am. Start work at 9am. Break for lunch at 12. Stop at 5:30pm. | L11: No habits at the end or beginning | M11: Raramente | N11: Raramente | O11: Mai | P11: Raramente | Q11: Mai | R11: Rarely does. It was tiring. | S11: 3–5 | T11: Canali di chat informali (es. #random su Slack), Non interagisco oltre il lavoro | U11: 2 | V11: 5 | W11: Very positively. It gives me more time and energy to socialise. | X11: Never. | Y11: Switch off my laptop. | Z11: Blocchi nel calendario, App per conoscere persone (es. Meetup), Un dispositivo o account separato per il lavoro | AA11: No, always had a good boundary I think | AB11: Harder to get to know your colleagues on a personally level. | AC11: A casa, in uno spazio condiviso (camera, cucina, soggiorno) | AI11: Orari standard, stesso fuso del mio team | AO11: 3–5 anni | AP11: Yes. I spend more time on leisure since I have more time available. | AQ11: Sometimes work gets busy with certain projects. I didn't do anything to help, I just got through it. | AR11: Always be responsive and present. Easy to be invisible when people can't see you in person. | AS11: If would consider hybrid if I changed jobs. As long as the commute was small. | AT11: Meno di 36 | BM11: No
A12: 46308.714 | B12: Sì, acconsento | C12: Sì, completamente da remoto (al massimo pochi giorni in ufficio all'anno) | D12: 30–35 | F12: Uomo | G12: Roma | H12: Programmatore | I12: Con il/la partner | J12: 3 o più volte a settimana | K12: Oggi ho iniziato alle 8.30 staccato alle 14.30 per pranzare, ho ripreso alle 15 e staccherò per le 18.30 | L12: No | M12: Spesso | N12: Spesso | O12: Spesso | P12: Raramente | Q12: Raramente | R12: Nervoso | S12: 1–2 | T12: Canali di chat informali (es. #random su Slack), Incontri dal vivo, retreat o offsite | U12: 4 | V12: 4 | W12: Più tempo per me, più spesso chiuso in casa | X12: Non mi capita perchè me ne strafotto. Se finisco tardi il giorno dopo inizio tardi. Mantengo mediamente sempre le 8 ore di lavoro anche se ci sono giorni in cui lavoro di più | Y12: Darmi degli obiettivi | Z12: Nessuno di questi | AA12: No mai | AB12: Personalmente non cambio nulla | AC12: A casa, in una stanza usata solo per lavorare | AI12: Orari standard, stesso fuso del mio team | AO12: 1–3 anni | AT12: Meno di 36 | BL12: No | BM12: No
A13: 46308.727 | B13: Sì, acconsento | C13: Ibrido: vado in ufficio o in sede regolarmente
A14: 46308.734 | B14: Sì, acconsento | C14: Sì, completamente da remoto (al massimo pochi giorni in ufficio all'anno) | D14: 36 o più | E14: Sì | F14: Uomo | G14: Francia, paesello sperduto in Alta Provenza alternandolo con la Liguria (comune di Sassello) | H14: Architect (sysadmin) | I14: Da solo/a | J14: Occasionalmente | K14: svegliato: 8, pausa 12-13, finito poco fa. In casa, ho parlato con vari soggetti colleghi e non da remoto. | L14: Nulla di speciale, orologio e stanza ufficio a parte. | M14: Spesso | N14: Spesso | O14: Mai | P14: A volte | Q14: A volte | R14: qui c'è una postilla, come contratto sarei dirigente (cadre sup) quindi NON ho un orario stabilito, sull'invadere non molto comunque, per ora le emergenze vere sono rare. Quando sono accadute erano giustificate quindi beh, era parte del lavoro. | S14: 6 o più | T14: Canali di chat informali (es. #random su Slack), VoIP, occasionali eventi (conferenze, cene o pranzi) | U14: 4 | V14: 4 | W14: mi ha permesso di lasciare la grande città per la montagna, dove si è numericamente meno ma si è animali sociali e non già ratti nell'esperimento di Calhoun (fogna del comportamento) isolati nella folla. Quindi direi che l'ha largamente migliorata. Ovviamente NON lo avrebbe fatto restando in appartamento, li chiuso in scatola penso avrei sofferto. Qui sono sul terrazzo in mezzo ai pini aprendo la porta "dell'ufficio" o aprendo quella di casa in giardino. Si fanno eventi nelle rispettive case secondo meteo/stagione e ci sono un po' di attività sul territorio, a differenza della Liguria e Italia in genere che è largamente MORTA fuori dalle città per urbanocentrismo. Non è in altri termini la natura del luogo ma il diverso stile di vita della popolazione a far la differenza. | X14: Non mi capita perché sono in un ambiente in cui si è sociali, ci si passa i pargoli tra le case, i nonni portano a spasso i più piccoli, gli altri van da soli e persino I CANI e i gatti sono sociali, vanno in giro da soli e si fan coccolare da tutti (se vi capita chessò di andare a Mons lo vedrete alla perfezione coi gatti nel centro del paesello). | Y14: Stanza ufficio, essenzialmente. | Z14: Un dispositivo o account separato per il lavoro | AA14: Mai provato. | AB14: L'ignoranza crassa IT che porta ancora avanti tante inefficienze economicamente ed umanamente insostenibili. Anche nelle aziende dove si fa telelavoro, dove c'è sempre qualcuno che non vuole capire e porta avanti modelli del passato spammando il mondo e complicando la vita al suo prossimo. | AC14: A casa, in una stanza usata solo per lavorare | AI14: Orari standard, stesso fuso del mio team | AO14: Più di 5 anni | AP14: Beh i primissimi tempi ero più "preoccupato d'esser sul pezzo", poi si è stabilito il ritmo e le cose sono andate senza frizione con pure un aumento della produttività, non una diminuzione. | AQ14: Cantiere di casa in ritardo, problemi con alcune ditte mi han reso scomoda la vita tra una VMC che ronzava montata male e piccoli altri problemi, ma diciamo molto materiali. | AR14: Anche chi fa IT spesso NON HA le basi dell'IT per lavorare con efficienza, ha come un rigetto mentale di dashboard, ticketing, cultura documentale, che rende scomodo il lavoro poco importa se in presenza o a distanza, è proprio un paradigma diverso che un tempo era la norma e non poteva esser diversamente per vari motivi, oggi dovrebbe esser superato ma per molti ancora non lo è. | AS14: MAI, MAI e poi MAI. | AT14: 36 o più | AU14: Non per i 35 ma più per i 30, prima uscivo di più, facevo tardi la notte, facevo feste and co, poi pian piano anche il mio gruppo d'amici tra bambini e impegni questo si è gradualmente ridotto e ha cambiato di conseguenza il modo di organizzare la vita. Non è specialmente legato al lavoro però il lavoro fa parte dello schema, fa parte dello schema esser lucido, aver una diversa responsabilità e questo influenza l'work-life balance. | AV14: In una relazione complicata si comincia a (ri)parlare di convivenza e figli e il remoto aiuta assai in ciò. Quindi questioni umane di coppia a parte (complicate come sempre e pure di più) il telelavoro dà una gran mano. | AW14: L'aver natura, bassa densità abitativa aiuta, essere in una zona turistica di un certo pregio aiuta, anche i residenti sono largamente internazionali, di difficile c'è solo da ex globetrotter con amici sparsi nel mondo il vedersi in persona, viaggio di meno, prima facevo miglia su miglia per tanti motivi, ora siamo tutti largamente accasati e non abbiamo più tanta voglia di passar frontiere e gestire vettori che sono sempre peggio come qualità. | AX14: In effetti il grosso delle cerchie ristrette di amici telelavora, quindi no, non ho ritmi diversi che si mettano in mezzo. | AY14: Rifiutare categoricamente la presenza fisica in ufficio, uno spreco inaccettabile per me sotto ogni aspetto. | AZ14: Beh, principalmente nessuno si sogna di richiamarmi in ufficio, resta per alcuni l'idea che chi lavora da remoto non lavora davvero, ma assai meno presente, non ci sono più granché inquietudini di carriera, avrò ancora avanzamenti ma alla fine anche cambiando lavoro mi cambia il login, non il luogo fisico, l'ambiente, l'itinere ecc. Da giovani ancora oggi c'è sospetto, spesso problemi di comprensione di cosa sia il lavoro, molti lo vivono come l'università, e una certa difficoltà IT, i giovani NON sono informatizzati, sono meno peggio dei sessantenni medi, ma sono mediamente assai mal messi in termini di basi, non riescono a capire perché devono studiare davvero come usare un desktop e come lavorare, abituati ad un mondo di webapp e mobile. L'assenza di IT insegnato a scuola, anche ad Ing. Informatica, Informatica, pesa tantissimo. | BA14: 2–10 anni | BB14: la possibilità di farlo. Nulla di più. L'avrei fatto dall'inizio. | BC14: Solo ignoranza IT, incapacità di riflettere autonomamente e agire prendendosi la propria responsabilità. Oggi i neolaureati medi han la stessa attitudine dell'ultimo degli operai di 15 anni fa. Non capiscono che il loro ruolo domanda una certa capacità d'azione autonoma, che non tutto è consequenziale né va come previsto, che serve anche iniziativa, non puro conformismo, esitazione, scarsa attenzione, in ultima analisi catena di montaggio. Non si tratta per chi è in team remoti come il mio caso di quiet quitting, si tratta proprio di mancanza di comprensione del proprio ruolo. | BD14: Si, regolarmente. Avviene onestamente meglio che in presenza SE si ha un'infra IT adeguata, desktop remoto e VoIP con bottiglietta da conferenza in stanza ufficio permettono di formarsi assai meglio che "sbirciare dalla scrivania", il problema è che molti non han la stanza ufficio, non han un ambiente per la bottiglietta da conferenza, spesso non capiscono perché servono e han paura a muoversi dalla città se casomai fossero richiamati in ufficio. Questo è abbastanza un ostacolo. Molti giovani ad es. non riescono a capire che è impensabile lavorare su laptop con la tastiera e lo schermo di questi. Non capiscono perché gli serve una postazione vera, la stanza ufficio, poi lamentano che fan male gli occhi, che fa male la schiena, sono stressati ecc per mancanza di attrezzature che nel presente oggettivamente nessuna azienda è interessata a dare ma neanche a chiedere perché diventerebbe troppo selettiva verso profili junior. | BE14: Comportamento adulto a parte direi nulla di speciale. | BF14: Energia e sonno ben migliori, movimento è un ni. Ni nel senso che sono nella natura, ho da seguire il giardino, gestire il bosco, esercizio fisico ne faccio, ma la voglia di scappare dalla città per far sport non c'è più non essendoci più la città. La postura direi che sia migliorata per una mera questione di postazione degna. | BG14: Assolutamente a mio agio. Poco a mio agio solo con chi non capisce come usare questi strumenti, ci sono giovani ad es. che HAN PAURA di disturbare a mandare una mail o chiamare quando serve, mentre magari trovano normale spammare in chat o non curarsi dello stato che han impostato. Ma non è lo strumento digitale il problema, è l'umano che non capisce come usarlo. | BH14: Penso che la sola differenza sia il momento ed il modo in cui mi sono avvicinato all'IT, non per lavoro ma nella vita privata di adolescente, rispetto ai giovani d'oggi. Sono ancora nato sul desktop FLOSS, oggi i più sono nati su tablet e passano a laptop, pochissimi arrivano al desktop prima del lavoro e non sono conseguentemente abituati ad un certo tipo di interazione. Per loro il computer è un soprammobile sempre disponibile, non un macchinario da usare seriamente in un luogo specifico. | BI14: Nulla mi manca onestamente... | BJ14: Beh, sono rimasto in contatto con alcuni dall'università, con alcuni dal lavoro globetrotterando, altri si sono aggiunti in loco, se proprio devo far una differenza l'aver lasciato la città mi ha tolto un po' la presenza fisica di persone di cultura medio-alta aumentando quelle di cultura medio-bassa, però questo sta poco alla volta cambiando man mano che aumentano i telelavoratori in loco. Dal lavoro i contatti sono più "professionali" che realmente amicali, ma ho sempre cercato di evitare di mescolare troppo i colleghi che non scelgo con gli amici che scelgo. | BK14: Poco. Ho genitori anziani che iniziano ad aver bisogno d'assistenza, e questo pesa, il telelavoro aiuta ma non c'è un'influenza specifica. | BL14: Nel tempo, ma parlo di almeno 5-8 anni di telelavoro, si è rilassati da così tanto che l'idea di vestirsi formalmente dà fastidio. Giacca&cravatta prima magari comuni diventano fastidiosi, un certo tipo di interazione formale diventa fastidioso, questo però resta ancora per chi vive "nel mondo classico" e può creare un minimo di frizione specie quando non si capisce e non si gestisce la cosa. Il remoto rende più facile interagire anche con soggetti difficili, ma al contempo fa scendere la tolleranza a questi in contesti di presenza. | BM14: Sì | BN14: rdtdiscuss@kfx.fr
A15: 46308.74 | B15: Sì, acconsento | C15: Sì, completamente da remoto (al massimo pochi giorni in ufficio all'anno) | D15: 36 o più | E15: No
A16: 46308.756 | B16: Sì, acconsento | C16: Ibrido: vado in ufficio o in sede regolarmente
A17: 46308.82 | B17: Sì, acconsento | C17: Sì, completamente da remoto (al massimo pochi giorni in ufficio all'anno) | D17: 30–35 | F17: Uomo | H17: AI engineer e Data Scientist | I17: Con i miei genitori / famiglia d'origine | J17: 3 o più volte a settimana | K17: Quella di oggi: ho parlato con i miei genitori e dei colleghi In genere faccio pausa a metà mattina, post pranzo e pomeriggio: generalmente faccio un rapporto tipo 1 ora lavoro - 5/10 minuti pausa | L17: Sveglia, sistemo letto, colazione per iniziare Poi combo caffè + sigaretta (e sapete come va a finire) per dare inizio Per la fine, non ho particolari rituali: chiudo tutto e via | M17: Raramente | N17: A volte | O17: Mai | P17: Mai | Q17: Raramente | R17: Cerco di non farlo: non ne vale la pena Quelle poche volte che l’ho fatto ho avuto una grande sensazione di “peso” inutile e ingiustificato | S17: 6 o più | T17: Canali di chat informali (es. #random su Slack), Incontri dal vivo, retreat o offsite, Vedo alcuni colleghi in privato, come amici | U17: 4 | V17: 5 | W17: Beh, semplicemente, vivendo con i miei, in un paese della Sicilia, ho praticamente zero spese “inutili”, come affitto ecc. Questo mi sta permettendo di concentrarmi su altro, come ristrutturazione della casa (di proprietà) e matrimonio | Y17: Nulla di particolare, diciamo che mi impongo degli “obblighi “: uno di questi è ad esempio andare ad allenarmi | Z17: Blocchi nel calendario | AB17: In realtà nulla: l’unica cosa che vorrei è sicuramente più garanzie: nell’ultima esperienza lavorativa sono stato costretto a dimettermi in quanto è stata presa la decisione della revoca dell’accordo del lavoro da remoto, imponendomi un ibrido al nord ( e di conseguenza un trasferimento) | AC17: A casa, in una stanza usata solo per lavorare | AI17: Orari standard, stesso fuso del mio team | AO17: Più di 5 anni | AP17: Ho sempre lavorato full-remote | AQ17: No in realtà no | AS17: Si, solo ed esclusivamente nel caso in cui l’ufficio non è lontano ore | AT17: Meno di 36 | BM17: Sì
A18: 46308.848 | B18: Sì, acconsento | C18: Sì, completamente da remoto (al massimo pochi giorni in ufficio all'anno) | D18: 36 o più | E18: No
A19: 46308.902 | B19: Sì, acconsento | C19: Sì, completamente da remoto (al massimo pochi giorni in ufficio all'anno) | D19: 36 o più | E19: No
A20: 46308.966 | B20: Sì, acconsento | C20: Sì, completamente da remoto (al massimo pochi giorni in ufficio all'anno) | D20: 30–35 | F20: Uomo | G20: Vico del Gargano (FG) | H20: Sviluppatore Software | I20: Da solo/a | J20: 1–2 volte a settimana | K20: Sveglia alle 6:30, palestra, attacco a lavorare alle 9, treno di call varie, poi sviluppo. Più che altro una pausa caffé e qualche pausa bagno. Pausa pranzo alle 13 cucino e mangio, sto al telefono con la mia compagna. Riattacco alle 14, altro lavoro, ca con il mio manager, chiudo alle 18. Qualche faccenda di casa, vado a far la spesa, vado a cenare dai miei genitori. Torno a casa, controllo le ultime modifiche della mia AI al mio progetto personale e le dò lavoro da fare per le prossime 24h. Letto. | L20: Nei giorni di palestra vado in palestra al mattino. | M20: A volte | N20: Raramente | O20: Raramente | P20: Mai | Q20: Raramente | R20: Normale. C'era un'emergenza vera ed ero l'unico che poteva gestirla in tempi utili. Per fortuna non avevo nulla di particolare da fare. Ma se fossi stato impegnato non sarei intervenuto io, e il mondo non sarebbe crollato comunque. | S20: 6 o più | T20: Incontri dal vivo, retreat o offsite | U20: 4 | V20: 3 | W20: Mi ha fornito le garanzie di vicinanza alla mia famiglia e soprattutto alla mia compagna, con cui presto andrò a convivere, con il progetto di costruire una famiglia. | X20: Non mi capita. Mi protegge il fatto che le persone a cui tengo sono vicine. Sono poche ma sono importanti. | Y20: Chiudo il mac, lascio il telefono aziendale a casa. | Z20: Fitness tracker o app sportive, Un dispositivo o account separato per il lavoro | AA20: No, non credo di aver provato nulla in questo senso. | AB20: Il problema principale del lavoro da remoto è che non esistono garanzie contrattuali nella legislazione italiana: la preoccupazione di perdere da un momento all'altro questo livello di benessere e soprattutto la vicinanza ai miei famigliari, per colpa di qualche cieca politica RTO o soft layoff, è ciò che mi dà più ansia in questo momento. Voglio avere la sicurezza di poter costruire una vita qui senza dover rinunciare alla mia carriera da un momento all'altro. | AC20: A casa, in una stanza usata solo per lavorare | AI20: Orari standard, stesso fuso del mio team | AO20: 1–3 anni | AT20: Meno di 36 | BM20: No
A21: 46308.984 | B21: Sì, acconsento | C21: Sì, completamente da remoto (al massimo pochi giorni in ufficio all'anno) | D21: 30–35 | F21: Uomo | G21: Cava de' Tirreni | H21: senior consultant | I21: Con il/la partner | J21: Occasionalmente | K21: sveglia, doccia, lavoro, pranzo, lavoro | L21: bo | M21: Raramente | N21: Mai | O21: Mai | P21: Mai | Q21: A volte | R21: male | S21: 6 o più | T21: Non interagisco oltre il lavoro | U21: 4 | V21: 5 | W21: più tempo libero da dedicare ai miei hobby | X21: bo | Y21: alle 18 spengo il pc | Z21: Non disturbare o orari per le notifiche | AA21: no | AB21: maggiore flessibilità oraria | AC21: A casa, in una stanza usata solo per lavorare | AI21: Orari standard, stesso fuso del mio team | AO21: 1–3 anni | AT21: Meno di 36 | BM21: No
A22: 46309.006 | B22: Sì, acconsento | C22: Sì, completamente da remoto (al massimo pochi giorni in ufficio all'anno) | D22: 36 o più | E22: Sì | F22: Uomo | G22: Milano | H22: Sviluppatore automazioni | I22: Con il/la partner | J22: 1–2 volte a settimana | K22: Lavoro solitamente sempre da casa, dove ho una postazione dedicata, raramente lavoro da bar o coworking se ho necessità (esempio se mi trovo fuori città). Sveglia per le 8/8:30, a volte passeggiata con cane prima di iniziare a lavorare, inizio a lavorare per le 9:30/10, pause caffe a metà mattinata e pausa pranzo (generalmente con la mia partner) verso le 13, riprendo a lavorare verso le 14 e finisco verso le 18:30/19. | L22: Nessun rituale particolare, solitamente subito dopo la fine del lavoro faccio una lunga passeggiata col cane | M22: A volte | N22: Spesso | O22: Raramente | P22: Mai | Q22: Mai | R22: Non succede quasi mai, quando succede solitamente non mi pesa perché non è mai un’ingerenza da parte di azienda o colleghi ma piuttosto io che mi porto avanti col lavoro e riorganizzo il tempo di lavoro, soprattutto quando so che in giornata ho lavorato meno tempo del previsto o che il giorno successivo ho impegni personali e vorrò staccare prima o iniziare più tardi. | S22: 3–5 | T22: Canali di chat informali (es. #random su Slack), Pause caffè virtuali / call sociali, Incontri dal vivo, retreat o offsite | U22: 4 | V22: 4 | W22: Premesso che non tornerei mai indietro. Aspetti negativi sicuramente un rischio di maggiore isolamento sociale e possibile “abbrutimento” casalingo (stare tutto il giorno in pigiama o simili, non avere chiari confini tra spazio personale e lavorativo, etc). Aspetti positivi molti di più: zero tempo di commuting e molto più tempo per me (non solo risparmio tempo per il tragitto casa-lavoro, ma in generale ho orari molto più flessibili), possibilità di viaggiare e lavorare lontano dalla sede di lavoro (inclusi periodi di lavoro da remoto da casa di familiari e genitori, che vivono lontani e non devo “sprecare” ferie per passare dei giorni/settimane con loro), in generale meno stress correlato agli aspetti “logistici” del lavoro (traffico o mezzi affollati, colleghi non necessariamente piacevoli con cui sei costretto a passare tempo, richieste di formalità nel vestiario, etc) | X22: Non mi capita mai. Convivo e ho un’ottima rete sociale al di fuori del lavoro. Aiuta molto anche avere un cane che ogni giorno mi “costringe” a uscire e fare lunghe passeggiate. | Y22: Fuori dall’orario di lavoro, silenzio tutte le notifiche relative al lavoro. | Z22: Blocchi nel calendario, Timer di concentrazione / Pomodoro, Non disturbare o orari per le notifiche, Fitness tracker o app sportive | AA22: No, mai successo | AB22: L’unica cosa che vorrei migliorare è praticare più spesso stretching e fare più spesso pause in cui mi alzo e cammino (per evitare dolori posturali) | AC22: A casa, in uno spazio condiviso (camera, cucina, soggiorno) | AI22: Lavoro con persone a 1–3 ore di differenza di fuso | AO22: 1–3 anni | AT22: 36 o più | AU22: Penso di aver migliorato la separazione tra lavoro e vita privata, e di aver migliorato la capacità di restare concentrato a lavoro | AV22: Maggiore “serietà” e concentrazione sul lavoro: ho trovato un’azienda “sana” e in cui mi sento valorizzato, che premia i risultati e non il tempo passato alla scrivania. Maggiore necessità di passare del tempo con la famiglia d’origine (per questioni da gestire), che posso fare facilmente grazie al l’abito da remoto. | AW22: Più facile: passioni comuni che richiedono socialità (giochi da tavolo) Più difficile: l’aumento delle responsabilità che riduce il tempo da dedicare alle amicizie (gestione domestica e finanziaria, cani o figli per chi li ha…) | AX22: Non influisce troppo, perché comunque ci si vede la sera o nei weekend. | AY22: Più sport | AZ22: Conosco pro e contro di entrambi i mondi, il che mi permette di riconoscere quel che è meglio per le mie esigenze. | BA22: 2–10 anni | BB22: Cambio di azienda | BC22: Non ho mai notato nulla di simile | BD22: Certo, con messaggi o videochiamate | BF22: Un bel mix. Di per sé probabilmente ha peggiorato movimento e postura, ma mi ha anche permesso di prendere un cane, che invece migliora questi aspetti. In generale, provo a fare sport (non essendo mai stato uno sportivo) | BG22: Molto a mio agio | BH22: I colleghi più giovani non conoscono la differenza, potrebbero sottovalutare pro e contro del lavoro da remoto, e forse fare più fatica a staccare (non avendo mai avuto l’esperienza di allontanarsi fisicamente dal lavoro) | BI22: Mi manca il rapporto con alcuni colleghi e la mensa aziendale (non dover pensare a cucinare il pranzo). Non mi manca per niente il tragitto casa-lavoro, il micro-management dei superiori, le interazioni “forzate” e non richieste che ti rompono il focus e rallentano i tempi | BJ22: Passioni comuni, conoscenze da scuola e università. Mi è capitato che alcuni amici (che vedevo anche fuori dall’ufficio) fossero persone che ho conosciti a lavoro, ma attualmente nessuno degli amici che frequento proviene dall’ambito lavorativo | BM22: No
A23: 46309.395 | B23: Sì, acconsento | C23: Sì, completamente da remoto (al massimo pochi giorni in ufficio all'anno) | D23: 30–35 | F23: Uomo | H23: Sviluppatore software | I23: Da solo/a | J23: 1–2 volte a settimana | K23: Faccio colazione, bagno, se il gatto si presenta alla finestra parlo con lui, poi riunioni e riunioni e ancora riunioni | L23: No. Alle 8.30 accendo Teams, alle 17.30 lo chiudo tranne in rare occasioni | M23: Raramente | N23: Raramente | O23: Mai | P23: A volte | Q23: A volte | R23: Inizio carriera 8+ anni fa: cliente non gestito dai superiori, mole di lavoro sproporzionata e un'altra commessa che ha bloccato completamente il mio tempo d'ufficio quando dovevo finire il lavoro per il suddetto cliente. Alla fine mi portavo il lavoro a casa | S23: 3–5 | T23: Canali di chat informali (es. #random su Slack), Vedo alcuni colleghi in privato, come amici | U23: 3 | V23: 3 | W23: Non ero uno socievole prima, non lo sono ora. È cambiato che adesso devo un po' impormi di uscire e fare attività, soprattutto nei weekend | X23: Non mi sento isolato. Vedere gli amici anche una sola volta a settimana nel weekend per me è sufficiente | Y23: Spengo telefono e PC aziendale | Z23: Timer di concentrazione / Pomodoro, Non disturbare o orari per le notifiche | AA23: Si, smesso perchè nella mia zona in montagna qualsiasi app non ha utenti | AB23: Le riunioni sono aumentate in modo non proporzionale alle effettive esigenze. Quindi meno riunioni e più blocchi di concentrazione | AC23: A casa, in una stanza usata solo per lavorare | AI23: Orari standard, stesso fuso del mio team | AO23: 3–5 anni | AP23: All'inizio uscivo meno nei weekend | AR23: Che non ti stanno facendo un regalo, perciò non dannarsi a dare sempre il 120% solo perchè puoi lavorare da casa | AS23: Lavoro ibrido valuterei se per una posizione davvero interessante ma nel mio caso qualsiasi posizione in ufficio implicherebbe dover affrontare più di 2 ore di auto o direttamente un trasloco. C'è stato un periodo che avevo più voglia di trasferirmi a prescindere dal tipo di contratto per motivi personali | AT23: Meno di 36 | BL23: Arrivare al lavoro a piedi è forse una delle cose che mi manca di più. Univa una cosa che comunque avrei dovuto fare a qualcosa che migliora la salute che ora devo necessariamente impormi di fare | BM23: No

Sheet Codebook
A1: Codice | B1: Etichetta | C1: Descrizione | D1: N. segmenti
A2: C01 | B2: Routine mattutina e caffè | C2: Include sveglia, colazione, caffè, igiene personale e piccole faccende domestiche prima di iniziare a lavorare. | D2: =COUNTIF(Codifica!$C$2:$C$76,"*"&A2&"*") -> 7
A3: C02 | B3: Attività fisica, sport e movimento | C3: Include palestra, sport, passeggiate all'aperto (anche con il cane), ripresa dell'attività fisica, stretching e pause attive. | D3: =COUNTIF(Codifica!$C$2:$C$76,"*"&A3&"*") -> 10
A4: C03 | B4: Riunioni e coordinamento sincrono | C4: Include call, daily, riunioni e allineamenti con colleghi o team, e la richiesta di ridurne il numero. | D4: =COUNTIF(Codifica!$C$2:$C$76,"*"&A4&"*") -> 10
A5: C04 | B5: Lavoro individuale e concentrazione | C5: Include lo svolgimento di task, sviluppo, monitoraggio e lavoro autonomo al computer, e la tutela di blocchi di concentrazione. | D5: =COUNTIF(Codifica!$C$2:$C$76,"*"&A5&"*") -> 8
A6: C05 | B6: Pause e pausa pranzo | C6: Include pause caffè, spuntini, micro-interruzioni, preparazione e consumo del pasto di metà giornata. | D6: =COUNTIF(Codifica!$C$2:$C$76,"*"&A6&"*") -> 7
A7: C06 | B7: Convivenza e famiglia | C7: Include interazioni, pasti o telefonate con partner, genitori e familiari, e la possibilità di stare più vicino ai propri cari. | D7: =COUNTIF(Codifica!$C$2:$C$76,"*"&A7&"*") -> 9
A8: C07 | B8: Postazione e spazio fisico di lavoro | C8: Include stanza o studio dedicato, spazi domestici condivisi, coworking e il non entrare nello spazio di lavoro fuori orario. | D8: =COUNTIF(Codifica!$C$2:$C$76,"*"&A8&"*") -> 9
A9: C08 | B9: Orari, impegni vincolanti e obiettivi | C9: Include orari di inizio e fine, chiusura a compiti completati, definizione di obiettivi e impegni personali (es. allenamento) che segnano lo stacco. | D9: =COUNTIF(Codifica!$C$2:$C$76,"*"&A9&"*") -> 13
A10: C09 | B10: Rituali tecnologici e disconnessione digitale | C10: Include accensione e spegnimento di PC e telefono aziendale, apertura e chiusura di app lavorative, silenziamento delle notifiche. | D10: =COUNTIF(Codifica!$C$2:$C$76,"*"&A10&"*") -> 9
A11: C10 | B11: Distacco mentale e assenza di separazione rigida | C11: Include dichiarazioni di non avere rituali o separazioni attive, tolleranza della sovrapposizione tra lavoro e vita privata, distacco mentale immediato a fine giornata. | D11: =COUNTIF(Codifica!$C$2:$C$76,"*"&A11&"*") -> 9
A12: C11 | B12: Flessibilità, tempo libero e tempo personale | C12: Include relax, hobby, svago, maggiore tempo per sé e richiesta di orari di lavoro più flessibili. | D12: =COUNTIF(Codifica!$C$2:$C$76,"*"&A12&"*") -> 10
A13: C12 | B13: Risparmio di tempo e di costi | C13: Include azzeramento o riduzione del pendolarismo e abbattimento di spese (trasporti, affitto, pranzi fuori). | D13: =COUNTIF(Codifica!$C$2:$C$76,"*"&A13&"*") -> 4
... A22: NP | B22: Risposta non pertinente, vuota o non informativa | C22: Include risposte prive di contenuto informativo (es. «bo», «No», «N/A», «Non saprei») o lasciate vuote. | D22: =COUNTIF(Codifica!$C$2:$C$76,"*"&A22&"*") -> 5

Sheet Codifica
A1: Riga | B1: Risposta | C1: Codici (separati da virgola) | D1: Etichette dei codici | E1: Colonna di origine (solo tracciabilità)
A2: 2 | B2: Passeggiata, lavoro creativo al mattino per me e per clienti, palestra + pranzo, dormita strategica, ancora lavoro blando fino alle 16-17. | C2: C04, C02, C05 | D2: Lavoro individuale e concentrazione, Attività fisica, sport e movimento, Pause e pausa pranzo | E2: K
A3: 2 | B3: Nella bella stagione una passeggiata prima di iniziare a lavorare | C3: C02 | D3: Attività fisica, sport e movimento | E3: L
A4: 2 | B4: Mi ha dato il controllo della mia intera esistenza, direi che è sufficiente. | C4: C11 | D4: Flessibilità, tempo libero e tempo personale | E4: W
A5: 2 | B5: Non lo faccio, ma il lavoro non invade la vita privata perché non arriva mai a picchi troppo stressanti. | C5: C10 | D5: Distacco mentale e assenza di separazione rigida | E5: Y
A6: 2 | B6: Vorrei aver ereditato case sparse per l'Italia come i migliori figli di papà per lavorare da posti diversi durante l'anno senza spendere tonnellate di denaro per farlo. | C6: C14 | D6: Rilocalizzazione e mobilità geografica | E6: AB
A7: 3 | B7: Mi sono svegliata alle 9. Alle 9:15 ho avuto il solito meeting di allineamento giornaliero (daily) fino alle 10. Alle 10 ho fatto colazione. Ho lavorato in autonomia fino alle 12. Alle 12 ho avuto un meeting. Mentre seguivo il meeting ho cucinato il pranzo. Alle 13 ho pranzato con la mia compagna. Alle 14:30 ho ripreso a lavorare. Alle 16:30 pausa caffè di 15 minuti. Ho lavorato fino alle 18. | C7: C03, C04, C06 | D7: Riunioni e coordinamento sincrono, Lavoro individuale e concentrazione, Convivenza e famiglia | E7: K
A8: 3 | B8: Accendo e spengo il PC ed esco dal mio studio. | C8: C09, C07 | D8: Rituali tecnologici e disconnessione digitale, Postazione e spazio fisico di lavoro | E8: L
A9: 3 | B9: In meglio! Più flessibilit e possibilità di vedere chi voglio dove voglio. | C9: C11, C13, C14 | D9: Flessibilità, tempo libero e tempo personale, Socialità extra-lavorativa e amicizie, Rilocalizzazione e mobilità geografica | E9: W
A10: 3 | B10: Ho un luogo adibito solo al lavoro, il mio studio. | C10: C07 | D10: Postazione e spazio fisico di lavoro | E10: Y
A11: 3 | B11: Non saprei | C11: NP | D11: Risposta non pertinente, vuota o non informativa | E11: AB
A12: 4 | B12: Colazione, call del mattino, caffè, lavoro, se ho tempi morti leggo qualcosa, pranzo, lavoro e poi o esco o vado in palestra | C12: C04, C03, C02 | D12: Lavoro individuale e concentrazione, Riunioni e coordinamento sincrono, Attività fisica, sport e movimento | E12: K
A13: 4 | B13: Mi faccio un caffè | C13: C01 | D13: Routine mattutina e caffè | E13: L
... A76: 23 | B76: Le riunioni sono aumentate in modo non proporzionale alle effettive esigenze. Quindi meno riunioni e più blocchi di concentrazione | C76: C03, C04 | D76: Riunioni e coordinamento sincrono, Lavoro individuale e concentrazione | E76: AB

Sheet Temi
A1: Tema | B1: Descrizione (2–3 frasi) | C1: Codici inclusi | D1: N. risposte (senza doppi conteggi) | E1: 2 citazioni di esempio (testuali, tra virgolette)
A2: Scansione operativa della giornata: lavoro individuale, riunioni e pause | B2: Questo macro-tema raccoglie il ritmo produttivo della giornata a distanza, scandito dall'alternanza tra lavoro individuale concentrato, riunioni di allineamento e brevi pause o pranzo. La giornata risulta fatta di blocchi sincroni e asincroni, con micro-interruzioni che ne regolano l'intensità. Emerge anche la richiesta di proteggere il tempo di concentrazione dall'eccesso di riunioni. | C2: C03, C04, C05 | D2: =SUMPRODUCT(SIGN(ISNUMBER(SEARCH("C03",Codifica!$C$2:$C$76))+ISNUMBER(SEARCH("C04",Codifica!$C$2:$C$76))+ISNUMBER(SEARCH("C05",Codifica!$C$2:$C$76)))) -> 14 | E2: "Call allineamento iniziale, svolgimento task, monitoraggio, allineamento colleghi, verifiche pomeridiane, stacco" "Le riunioni sono aumentate in modo non proporzionale alle effettive esigenze. Quindi meno riunioni e più blocchi di concentrazione"
A3: Confini temporali, spaziali e digitali: orari, postazione e disconnessione | B3: Il macro-tema descrive come si costruiscono i confini tra lavoro e vita privata in assenza del pendolarismo: orari fissi o chiusura a compiti completati, una stanza o postazione dedicata, rituali tecnologici di accensione e spegnimento, silenziamento di notifiche e telefono aziendale. Accanto a questi dispositivi concreti compare un atteggiamento di distacco mentale o di tolleranza della sovrapposizione, in cui la separazione non è formalizzata in rituali. | C3: C07, C08, C09, C10 | D3: =SUMPRODUCT(SIGN(ISNUMBER(SEARCH("C07",Codifica!$C$2:$C$76))+ISNUMBER(SEARCH("C08",Codifica!$C$2:$C$76))+ISNUMBER(SEARCH("C09",Codifica!$C$2:$C$76))+ISNUMBER(SEARCH("C10",Codifica!$C$2:$C$76)))) -> 29 | E3: "Ho un luogo adibito solo al lavoro, il mio studio." "No. Alle 8.30 accendo Teams, alle 17.30 lo chiudo tranne in rare occasioni"
A4: Cura di sé, tempo restituito e quotidianità | B4: Questo tema riunisce le pratiche e i benefici legati alla cura di sé: routine mattutine e caffè, attività fisica e passeggiate, tempo libero e flessibilità, risparmio di tempo e di costi grazie all'assenza di spostamenti. Il lavoro da remoto è vissuto come una risorsa che restituisce tempo ed energie per salute, hobby e vita quotidiana, anche se qualcuno segnala la necessità di compensare la sedentarietà. | C4: C01, C02, C11, C12 | D4: =SUMPRODUCT(SIGN(ISNUMBER(SEARCH("C01",Codifica!$C$2:$C$76))+ISNUMBER(SEARCH("C02",Codifica!$C$2:$C$76))+ISNUMBER(SEARCH("C11",Codifica!$C$2:$C$76))+ISNUMBER(SEARCH("C12",Codifica!$C$2:$C$76)))) -> 28 | E4: "Posso finalmente riprendere a fare sport dato che non devo sprecare ore di pendolarismo" "più tempo libero da dedicare ai miei hobby"
A5: Affetti, amicizie e radicamento territoriale | B5: Il macro-tema mette in luce lo spostamento della socialità verso la sfera degli affetti: partner, famiglia d'origine e amici di lunga data. La libertà di scegliere dove vivere consente di lasciare le grandi città, tornare nei luoghi d'origine o stare vicino ai propri cari, mentre il tempo e l'energia recuperati alimentano la vita sociale e le relazioni significative. | C5: C06, C13, C14 | D5: =SUMPRODUCT(SIGN(ISNUMBER(SEARCH("C06",Codifica!$C$2:$C$76))+ISNUMBER(SEARCH("C13",Codifica!$C$2:$C$76))+ISNUMBER(SEARCH("C14",Codifica!$C$2:$C$76)))) -> 14 | E5: "Mi ha fornito le garanzie di vicinanza alla mia famiglia e soprattutto alla mia compagna, con cui presto andrò a convivere, con il progetto di costruire una famiglia." "mi ha permesso di lasciare la grande città per la montagna"
A6: Relazioni professionali e rischio di isolamento | B6: Il tema riguarda l'altra faccia del remoto: la rarefazione dei rapporti informali con i colleghi, il desiderio di legami meno distaccati e di incontri periodici dal vivo, e il rischio di isolamento domestico. In alcuni casi la socialità fuori dal lavoro richiede uno sforzo intenzionale, come imporsi di uscire nei weekend. | C6: C15, C16 | D6: =SUMPRODUCT(SIGN(ISNUMBER(SEARCH("C15",Codifica!$C$2:$C$76))+ISNUMBER(SEARCH("C16",Codifica!$C$2:$C$76)))) -> 8 | E6: "Parlo meno con colleghi e li conosco meno, forse imparo meno velocemente ma son più performante perché perdo molto meno tempo" "Più tempo per me, più spesso chiuso in casa"
A7: Tutele e qualità dell'organizzazione del lavoro a distanza | B7: Questo macro-tema raccoglie le valutazioni complessive sul modello organizzativo: da un lato la soddisfazione per l'assetto attuale, vissuto come diritto e libertà, dall'altro la richiesta di garanzie contrattuali contro revoche del remoto o politiche di rientro in sede. Include anche la critica a modelli gestionali obsoleti e a comunicazioni dispersive che rendono meno efficiente il lavoro a distanza. | C7: C17, C18, C19 | D7: =SUMPRODUCT(SIGN(ISNUMBER(SEARCH("C17",Codifica!$C$2:$C$76))+ISNUMBER(SEARCH("C18",Codifica!$C$2:$C$76))+ISNUMBER(SEARCH("C19",Codifica!$C$2:$C$76)))) -> 6 | E7: "Il problema principale del lavoro da remoto è che non esistono garanzie contrattuali nella legislazione italiana" "Non cambierei nulla, per me lavorare da remoto e' un diritto che tutti dovrebbero avere."
